pyrmv/__init__.py
pyrmv/classes/__init__.py
pyrmv/classes/board.py
pyrmv/classes/client.py
pyrmv/classes/gis.py
pyrmv/classes/journey.py
pyrmv/classes/leg.py
pyrmv/classes/message.py
pyrmv/classes/platform_type.py
pyrmv/classes/stop.py
pyrmv/classes/ticket.py
pyrmv/classes/trip.py
pyrmv/const/__init__.py
pyrmv/const/product.py
pyrmv/enums/__init__.py
pyrmv/enums/aff_journey_mode.py
pyrmv/enums/aff_journey_stop_mode.py
pyrmv/enums/auto_name.py
pyrmv/enums/board_type.py
pyrmv/enums/filter_mode.py
pyrmv/enums/lang.py
pyrmv/enums/location_type.py
pyrmv/enums/platform_type_type.py
pyrmv/enums/product.py
pyrmv/enums/rt_mode.py
pyrmv/enums/search_mode.py
pyrmv/enums/selection_mode.py
pyrmv/errors/__init__.py
pyrmv/errors/api_errors.py
pyrmv/errors/int_errors.py
pyrmv/errors/not_ready.py
pyrmv/errors/ps_errors.py
pyrmv/errors/sot_errors.py
pyrmv/errors/svc_errors.py
pyrmv/errors/unknown_error.py
pyrmv/raw/__init__.py
pyrmv/raw/board_arrival.py
pyrmv/raw/board_departure.py
pyrmv/raw/him_search.py
pyrmv/raw/journey_detail.py
pyrmv/raw/stop_by_coords.py
pyrmv/raw/stop_by_name.py
pyrmv/raw/trip_find.py
pyrmv/raw/trip_recon.py
pyrmv/utility/__init__.py
pyrmv/utility/find_exception.py
pyrmv/utility/journey_ref_converter.py
pyrmv/utility/weekdays_bitmask.py
pyrmv-0.5.0.dist-info/licenses/LICENSE
pyrmv-0.5.0.dist-info/METADATA
pyrmv-0.5.0.dist-info/WHEEL
pyrmv-0.5.0.dist-info/top_level.txt
pyrmv-0.5.0.dist-info/RECORD
