Metadata-Version: 2.4
Name: pyrmv
Version: 0.5.0
Summary: Small module that makes your journey with RMV REST API somehow easier.
Author-email: Profitroll <profitroll@end-play.xyz>
Maintainer-email: Profitroll <profitroll@end-play.xyz>
License: MIT
Project-URL: Homepage, https://git.end-play.xyz/profitroll/PythonRMV
Project-URL: Source, https://git.end-play.xyz/profitroll/PythonRMV
Project-URL: Tracker, https://git.end-play.xyz/profitroll/PythonRMV/issues
Project-URL: Documentation, https://git.end-play.xyz/profitroll/PythonRMV/wiki
Classifier: Development Status :: 3 - Alpha
Classifier: Intended Audience :: Developers
Classifier: License :: OSI Approved :: MIT License
Classifier: Operating System :: OS Independent
Classifier: Programming Language :: Python :: 3
Classifier: Programming Language :: Python :: 3.9
Classifier: Programming Language :: Python :: 3.10
Classifier: Programming Language :: Python :: 3.11
Classifier: Programming Language :: Python :: 3.12
Classifier: Topic :: Software Development :: Libraries :: Python Modules
Classifier: Topic :: Utilities
Requires-Python: >=3.9
License-File: LICENSE
Requires-Dist: requests~=2.32.3
Requires-Dist: xmltodict~=0.14.0
Requires-Dist: isodate~=0.7.0
Provides-Extra: dev
Requires-Dist: black~=25.1.0; extra == "dev"
Requires-Dist: isort==5.13.2; extra == "dev"
Requires-Dist: mypy~=1.15.0; extra == "dev"
Requires-Dist: pylint<3.4.0,==3.3.7; extra == "dev"
Requires-Dist: pytest-cov~=6.1.0; extra == "dev"
Requires-Dist: pytest~=8.3.2; extra == "dev"
Requires-Dist: tox==4.25.0; extra == "dev"
Requires-Dist: types-ujson~=5.10.0.20240515; extra == "dev"
Provides-Extra: dist
Requires-Dist: build==1.2.2.post1; extra == "dist"
Requires-Dist: twine~=6.1.0; extra == "dist"
Provides-Extra: speed
Requires-Dist: ujson~=5.10.0; extra == "speed"
Dynamic: license-file
